AtomFeixingShouceZhongwenban/README.md
AtomFeixingShouceZhongwenban/__init__.py
AtomFeixingShouceZhongwenban/__main__.py
AtomFeixingShouceZhongwenban/file.epub
AtomFeixingShouceZhongwenban/index.html
AtomFeixingShouceZhongwenban/css/__init__.py
AtomFeixingShouceZhongwenban/css/annotations.css
AtomFeixingShouceZhongwenban/css/main.css
AtomFeixingShouceZhongwenban/css/normalize.css
AtomFeixingShouceZhongwenban/css/popup.css
AtomFeixingShouceZhongwenban/font/__init__.py
AtomFeixingShouceZhongwenban/font/fontello.eot
AtomFeixingShouceZhongwenban/font/fontello.svg
AtomFeixingShouceZhongwenban/font/fontello.ttf
AtomFeixingShouceZhongwenban/font/fontello.woff
AtomFeixingShouceZhongwenban/img/__init__.py
AtomFeixingShouceZhongwenban/img/annotator-glyph-sprite.png
AtomFeixingShouceZhongwenban/img/annotator-icon-sprite.png
AtomFeixingShouceZhongwenban/img/apple-touch-icon.png
AtomFeixingShouceZhongwenban/img/cancelfullscreen.png
AtomFeixingShouceZhongwenban/img/close.png
AtomFeixingShouceZhongwenban/img/fullscreen.png
AtomFeixingShouceZhongwenban/img/loader.gif
AtomFeixingShouceZhongwenban/img/menu-icon.png
AtomFeixingShouceZhongwenban/img/save.png
AtomFeixingShouceZhongwenban/img/saved.png
AtomFeixingShouceZhongwenban/img/settings-s.png
AtomFeixingShouceZhongwenban/img/settings.png
AtomFeixingShouceZhongwenban/img/star.png
AtomFeixingShouceZhongwenban/js/__init__.py
AtomFeixingShouceZhongwenban/js/epub.js
AtomFeixingShouceZhongwenban/js/epub.min.js
AtomFeixingShouceZhongwenban/js/epub.min.map
AtomFeixingShouceZhongwenban/js/hooks.min.js
AtomFeixingShouceZhongwenban/js/hooks.min.map
AtomFeixingShouceZhongwenban/js/reader.js
AtomFeixingShouceZhongwenban/js/reader.js.map
AtomFeixingShouceZhongwenban/js/reader.min.js
AtomFeixingShouceZhongwenban/js/reader.min.map
AtomFeixingShouceZhongwenban/js/hooks/__init__.py
AtomFeixingShouceZhongwenban/js/hooks/extensions/__init__.py
AtomFeixingShouceZhongwenban/js/hooks/extensions/highlight.js
atom_feixing_shouce_zhongwenban-2024.3.1.0.dist-info/METADATA
atom_feixing_shouce_zhongwenban-2024.3.1.0.dist-info/WHEEL
atom_feixing_shouce_zhongwenban-2024.3.1.0.dist-info/entry_points.txt
atom_feixing_shouce_zhongwenban-2024.3.1.0.dist-info/top_level.txt
atom_feixing_shouce_zhongwenban-2024.3.1.0.dist-info/RECORD
